{
  "_comment": "알람 코드 DB - 설비별 알람 코드를 아래 형식으로 추가하세요.",
  "_format": "{ \"코드\": { \"name\": \"알람명\", \"meaning\": \"의미\", \"causes\": [\"원인1\"], \"actions\": [\"조치1\"] } }",
  "E001": {
    "name": "과전류 알람",
    "meaning": "모터 전류가 설정값 이상으로 검출됨",
    "causes": ["과부하", "모터 권선 절연 불량", "베어링 마모"],
    "actions": ["부하 확인 및 경감", "절연 저항 측정", "베어링 교체 검토"]
  },
  "E002": {
    "name": "과열 알람",
    "meaning": "설비 온도가 허용 범위 초과",
    "causes": ["냉각 팬 고장", "필터 막힘", "주변 온도 상승"],
    "actions": ["냉각 팬 점검", "필터 청소 또는 교체", "환기 확인"]
  },
  "E003": {
    "name": "통신 오류",
    "meaning": "상위 제어기와의 통신 단절",
    "causes": ["케이블 단선", "노이즈 간섭", "프로토콜 설정 불일치"],
    "actions": ["통신 케이블 점검", "실드 및 접지 확인", "통신 파라미터 확인"]
  },
  "W001": {
    "name": "저전압 경보",
    "meaning": "입력 전압이 하한값 근접",
    "causes": ["전원 품질 불량", "케이블 압강하 과다"],
    "actions": ["입력 전압 측정", "케이블 단면적 검토"]
  }
}
